Pygroove-1.0.2.dist-info/DESCRIPTION.rst
Pygroove-1.0.2.dist-info/METADATA
Pygroove-1.0.2.dist-info/RECORD
Pygroove-1.0.2.dist-info/WHEEL
Pygroove-1.0.2.dist-info/metadata.json
Pygroove-1.0.2.dist-info/top_level.txt
pygroove/__init__.py
pygroove/pygroove.py
